[{"date_added":"2026-07-18T00:52:00.000Z","id":"indicator--5c9dbdba-9fe8-5336-b685-ae0de0bc7ed8","media_type":"application/stix+json;version=2.1","version":"2026-07-18T00:52:00.000Z"},{"date_added":"2026-07-18T00:52:00.000Z","id":"indicator--977f8ae0-608c-50ef-862d-4f7501d6d809","media_type":"application/stix+json;version=2.1","version":"2026-07-18T00:52:00.000Z"},{"date_added":"2026-07-18T08:09:00.000Z","id":"indicator--45e49a05-8981-5cd5-acc9-903a51189825","media_type":"application/stix+json;version=2.1","version":"2026-07-18T08:09:00.000Z"},{"date_added":"2026-07-18T08:09:00.000Z","id":"indicator--7259ad55-2aba-5c3a-ba7d-dcc39494b243","media_type":"application/stix+json;version=2.1","version":"2026-07-18T08:09:00.000Z"},{"date_added":"2026-07-18T08:09:00.000Z","id":"indicator--e566726d-c23a-507c-a5f7-7ad8fcbc239c","media_type":"application/stix+json;version=2.1","version":"2026-07-18T08:09:00.000Z"},{"date_added":"2026-07-18T08:12:00.000Z","id":"indicator--fac3a085-7c6a-5881-9cea-a451c4be3956","media_type":"application/stix+json;version=2.1","version":"2026-07-18T08:12:00.000Z"},{"date_added":"2026-07-18T08:16:00.000Z","id":"indicator--3489aed2-54c8-5c1f-861e-4ae72e72b25e","media_type":"application/stix+json;version=2.1","version":"2026-07-18T08:16:00.000Z"},{"date_added":"2026-07-18T08:16:00.000Z","id":"indicator--74963e92-9bdb-5810-ac87-f753de7f8e40","media_type":"application/stix+json;version=2.1","version":"2026-07-18T08:16:00.000Z"},{"date_added":"2026-07-18T08:16:00.000Z","id":"indicator--89a5a5cc-95fd-585e-8824-d86a5996dafc","media_type":"application/stix+json;version=2.1","version":"2026-07-18T08:16:00.000Z"},{"date_added":"2026-07-18T08:16:00.000Z","id":"indicator--93f42328-c3e7-54d5-b534-6d7fbe8c7ac8","media_type":"application/stix+json;version=2.1","version":"2026-07-18T08:16:00.000Z"},{"date_added":"2026-07-18T08:16:00.000Z","id":"indicator--e43121c6-314f-580c-87e6-90572496d60d","media_type":"application/stix+json;version=2.1","version":"2026-07-18T08:16:00.000Z"},{"date_added":"2026-07-18T08:19:00.000Z","id":"indicator--38c92fd6-e61c-5e22-b567-94dbbc7e844f","media_type":"application/stix+json;version=2.1","version":"2026-07-18T08:19:00.000Z"},{"date_added":"2026-07-18T08:19:00.000Z","id":"indicator--8d5aeb8d-9ec5-5d19-917f-00663dc30fd7","media_type":"application/stix+json;version=2.1","version":"2026-07-18T08:19:00.000Z"},{"date_added":"2026-07-18T08:19:00.000Z","id":"indicator--ccf8a669-8266-5684-b08e-5998a2315b9d","media_type":"application/stix+json;version=2.1","version":"2026-07-18T08:19:00.000Z"},{"date_added":"2026-07-18T08:22:00.000Z","id":"indicator--12f65093-1a91-5f41-8cc8-36c93380a35a","media_type":"application/stix+json;version=2.1","version":"2026-07-18T08:22:00.000Z"},{"date_added":"2026-07-18T08:22:00.000Z","id":"indicator--1b0e1c62-9809-5e27-a48e-31f2ee47385c","media_type":"application/stix+json;version=2.1","version":"2026-07-18T08:22:00.000Z"},{"date_added":"2026-07-18T08:22:00.000Z","id":"indicator--6455f515-f3c9-5a80-a611-32e92009ecef","media_type":"application/stix+json;version=2.1","version":"2026-07-18T08:22:00.000Z"},{"date_added":"2026-07-18T08:22:00.000Z","id":"indicator--d8ba7639-91ee-5a5c-b95e-9c25e00f0817","media_type":"application/stix+json;version=2.1","version":"2026-07-18T08:22:00.000Z"},{"date_added":"2026-07-18T08:26:00.000Z","id":"indicator--31dde0b8-f788-58eb-9fd2-f90ee0e95c18","media_type":"application/stix+json;version=2.1","version":"2026-07-18T08:26:00.000Z"},{"date_added":"2026-07-18T08:33:00.000Z","id":"indicator--091305b6-da22-5041-aa8e-535532e02d06","media_type":"application/stix+json;version=2.1","version":"2026-07-18T08:33:00.000Z"},{"date_added":"2026-07-18T08:33:00.000Z","id":"indicator--39eb4f9c-3c64-5a13-a9f1-c25896201935","media_type":"application/stix+json;version=2.1","version":"2026-07-18T08:33:00.000Z"},{"date_added":"2026-07-18T08:33:00.000Z","id":"indicator--9a9dff60-c730-5373-9267-89c88e1cc5ec","media_type":"application/stix+json;version=2.1","version":"2026-07-18T08:33:00.000Z"},{"date_added":"2026-07-18T08:33:00.000Z","id":"indicator--aca98fc5-381f-52b9-b6f2-5295324d7786","media_type":"application/stix+json;version=2.1","version":"2026-07-18T08:33:00.000Z"},{"date_added":"2026-07-18T08:47:00.000Z","id":"indicator--3f2c89df-d59e-5d57-8611-521cc90d50d6","media_type":"application/stix+json;version=2.1","version":"2026-07-18T08:47:00.000Z"},{"date_added":"2026-07-18T09:02:00.000Z","id":"indicator--1970192b-85fb-5307-abaa-488bd859afd2","media_type":"application/stix+json;version=2.1","version":"2026-07-18T09:02:00.000Z"},{"date_added":"2026-07-18T09:02:00.000Z","id":"indicator--428cd12f-bf19-5f3a-9bcb-7197d3c29a88","media_type":"application/stix+json;version=2.1","version":"2026-07-18T09:02:00.000Z"},{"date_added":"2026-07-18T09:02:00.000Z","id":"indicator--45b74f48-c516-5b45-a9d8-0f10824d629e","media_type":"application/stix+json;version=2.1","version":"2026-07-18T09:02:00.000Z"},{"date_added":"2026-07-18T09:02:00.000Z","id":"indicator--561cf184-e4e1-5358-a3a0-1d5cb9285aa0","media_type":"application/stix+json;version=2.1","version":"2026-07-18T09:02:00.000Z"},{"date_added":"2026-07-18T09:02:00.000Z","id":"indicator--6c05a573-e281-5ea2-bc45-a145641370bd","media_type":"application/stix+json;version=2.1","version":"2026-07-18T09:02:00.000Z"},{"date_added":"2026-07-18T09:02:00.000Z","id":"indicator--74ca30a2-7bec-5319-a8b2-93e5c07713b5","media_type":"application/stix+json;version=2.1","version":"2026-07-18T09:02:00.000Z"},{"date_added":"2026-07-18T09:02:00.000Z","id":"indicator--e90a0875-5e26-531f-9083-4bc9588f3f9c","media_type":"application/stix+json;version=2.1","version":"2026-07-18T09:02:00.000Z"},{"date_added":"2026-07-18T09:07:00.000Z","id":"indicator--367de397-194c-53be-aeb8-f79688afef98","media_type":"application/stix+json;version=2.1","version":"2026-07-18T09:07:00.000Z"},{"date_added":"2026-07-18T09:07:00.000Z","id":"indicator--c81dbb4a-e6ac-5dae-a5f8-93911891c34c","media_type":"application/stix+json;version=2.1","version":"2026-07-18T09:07:00.000Z"},{"date_added":"2026-07-18T09:07:00.000Z","id":"indicator--fe2308fb-0603-524d-803e-331db6838fda","media_type":"application/stix+json;version=2.1","version":"2026-07-18T09:07:00.000Z"},{"date_added":"2026-07-18T09:20:00.000Z","id":"indicator--4d389f25-955e-506e-8abb-6b5ddf91f009","media_type":"application/stix+json;version=2.1","version":"2026-07-18T09:20:00.000Z"},{"date_added":"2026-07-18T09:24:00.000Z","id":"indicator--3bdfa641-64d8-5e50-a701-6ec232af1cf3","media_type":"application/stix+json;version=2.1","version":"2026-07-18T09:24:00.000Z"},{"date_added":"2026-07-18T09:24:00.000Z","id":"indicator--53ca0b8d-54d1-58f8-8d08-554196e5b37e","media_type":"application/stix+json;version=2.1","version":"2026-07-18T09:24:00.000Z"},{"date_added":"2026-07-18T09:24:00.000Z","id":"indicator--ece14be3-164b-540f-a592-e951efd46d68","media_type":"application/stix+json;version=2.1","version":"2026-07-18T09:24:00.000Z"},{"date_added":"2026-07-18T09:29:00.000Z","id":"indicator--a1b3339f-509f-5006-8ed5-36c078c454f8","media_type":"application/stix+json;version=2.1","version":"2026-07-18T09:29:00.000Z"},{"date_added":"2026-07-18T09:29:00.000Z","id":"indicator--c9d5f1a7-6176-5744-ab39-76bca54e0705","media_type":"application/stix+json;version=2.1","version":"2026-07-18T09:29:00.000Z"},{"date_added":"2026-07-18T12:10:00.000Z","id":"indicator--17c5b575-ebe7-5506-973c-35c61f1d6282","media_type":"application/stix+json;version=2.1","version":"2026-07-18T12:10:00.000Z"},{"date_added":"2026-07-18T12:10:00.000Z","id":"indicator--dd968c2e-385e-5f85-beab-ab77c9d31663","media_type":"application/stix+json;version=2.1","version":"2026-07-18T12:10:00.000Z"},{"date_added":"2026-07-18T12:16:00.000Z","id":"indicator--64c41b04-b6f8-569f-a5d8-fb04061c92dd","media_type":"application/stix+json;version=2.1","version":"2026-07-18T12:16:00.000Z"},{"date_added":"2026-07-18T12:16:00.000Z","id":"indicator--fac6413c-40ae-5441-8cd7-587ad9e3bf1b","media_type":"application/stix+json;version=2.1","version":"2026-07-18T12:16:00.000Z"},{"date_added":"2026-07-18T14:01:00.000Z","id":"indicator--f600a7f8-7920-576c-a4df-89f508834253","media_type":"application/stix+json;version=2.1","version":"2026-07-18T14:01:00.000Z"},{"date_added":"2026-07-18T14:18:00.000Z","id":"indicator--1fc7daeb-3543-51ef-ae9e-575621f0eef9","media_type":"application/stix+json;version=2.1","version":"2026-07-18T14:18:00.000Z"},{"date_added":"2026-07-18T14:18:00.000Z","id":"indicator--462303c0-ba14-5553-9228-5518cf30e432","media_type":"application/stix+json;version=2.1","version":"2026-07-18T14:18:00.000Z"},{"date_added":"2026-07-18T14:18:00.000Z","id":"indicator--4b254fdd-43aa-512a-8862-59048ffe04d3","media_type":"application/stix+json;version=2.1","version":"2026-07-18T14:18:00.000Z"},{"date_added":"2026-07-18T14:18:00.000Z","id":"indicator--4c8ddd46-96d9-5c2d-9cf9-bdc6c750de62","media_type":"application/stix+json;version=2.1","version":"2026-07-18T14:18:00.000Z"},{"date_added":"2026-07-18T14:18:00.000Z","id":"indicator--4fa27c1e-71b7-58c8-ab17-11b7f374a1d0","media_type":"application/stix+json;version=2.1","version":"2026-07-18T14:18:00.000Z"},{"date_added":"2026-07-18T14:18:00.000Z","id":"indicator--4fd782d8-6a65-5087-bdf5-7962f56690bf","media_type":"application/stix+json;version=2.1","version":"2026-07-18T14:18:00.000Z"},{"date_added":"2026-07-18T14:18:00.000Z","id":"indicator--5a16f108-85b4-5693-9d43-1e779c844654","media_type":"application/stix+json;version=2.1","version":"2026-07-18T14:18:00.000Z"},{"date_added":"2026-07-18T14:18:00.000Z","id":"indicator--8e3eb49b-5534-5e67-8660-b88c23d2e3ba","media_type":"application/stix+json;version=2.1","version":"2026-07-18T14:18:00.000Z"},{"date_added":"2026-07-18T14:18:00.000Z","id":"indicator--a2e87fff-ec7a-5bc9-8ba3-526a7cef5127","media_type":"application/stix+json;version=2.1","version":"2026-07-18T14:18:00.000Z"},{"date_added":"2026-07-18T14:18:00.000Z","id":"indicator--be951a1e-3774-5042-adc4-ac3e76fec5d2","media_type":"application/stix+json;version=2.1","version":"2026-07-18T14:18:00.000Z"},{"date_added":"2026-07-18T14:34:00.000Z","id":"indicator--c3ece053-bb40-50de-8a81-9ca58ea7102f","media_type":"application/stix+json;version=2.1","version":"2026-07-18T14:34:00.000Z"},{"date_added":"2026-07-18T14:34:00.000Z","id":"indicator--f4fa6b46-9560-5898-9d8d-0f1f4f1da081","media_type":"application/stix+json;version=2.1","version":"2026-07-18T14:34:00.000Z"},{"date_added":"2026-07-18T15:02:00.000Z","id":"indicator--1e8335a3-0ea3-5e1c-9d8e-6dde64a9becb","media_type":"application/stix+json;version=2.1","version":"2026-07-18T15:02:00.000Z"},{"date_added":"2026-07-18T15:02:00.000Z","id":"indicator--2fbcffd3-8787-50bd-adef-185f6deb74e3","media_type":"application/stix+json;version=2.1","version":"2026-07-18T15:02:00.000Z"},{"date_added":"2026-07-18T15:02:00.000Z","id":"indicator--407b9a70-ca2d-511e-abe0-ce9e62220997","media_type":"application/stix+json;version=2.1","version":"2026-07-18T15:02:00.000Z"},{"date_added":"2026-07-18T15:02:00.000Z","id":"indicator--a2af0d5c-df79-5dc3-b2fb-185a140a0fe5","media_type":"application/stix+json;version=2.1","version":"2026-07-18T15:02:00.000Z"},{"date_added":"2026-07-18T15:02:00.000Z","id":"indicator--cf76b4ee-1369-5cd9-a201-42ed98e7d245","media_type":"application/stix+json;version=2.1","version":"2026-07-18T15:02:00.000Z"},{"date_added":"2026-07-18T19:15:00.000Z","id":"indicator--0bebce00-3633-5f63-9be4-f0ae9480d936","media_type":"application/stix+json;version=2.1","version":"2026-07-18T19:15:00.000Z"},{"date_added":"2026-07-18T19:15:00.000Z","id":"indicator--0c6384c0-34df-5aa0-84bf-330b2c81f396","media_type":"application/stix+json;version=2.1","version":"2026-07-18T19:15:00.000Z"},{"date_added":"2026-07-18T19:15:00.000Z","id":"indicator--0cbc8a00-01a6-5c89-990c-4d6727431e50","media_type":"application/stix+json;version=2.1","version":"2026-07-18T19:15:00.000Z"},{"date_added":"2026-07-18T19:15:00.000Z","id":"indicator--15ae54d9-bc91-524e-a4d9-b218f998534b","media_type":"application/stix+json;version=2.1","version":"2026-07-18T19:15:00.000Z"},{"date_added":"2026-07-18T19:15:00.000Z","id":"indicator--1789cd55-4552-5b1f-b556-f7a4709e8ead","media_type":"application/stix+json;version=2.1","version":"2026-07-18T19:15:00.000Z"},{"date_added":"2026-07-18T19:15:00.000Z","id":"indicator--1ec233dd-dfa1-5718-92d6-657f346bb07e","media_type":"application/stix+json;version=2.1","version":"2026-07-18T19:15:00.000Z"},{"date_added":"2026-07-18T19:15:00.000Z","id":"indicator--4fa6aca2-57d7-5477-8925-3aac1fb25c63","media_type":"application/stix+json;version=2.1","version":"2026-07-18T19:15:00.000Z"},{"date_added":"2026-07-18T19:15:00.000Z","id":"indicator--5252e65f-2cc3-52ae-a58e-19c17a773f33","media_type":"application/stix+json;version=2.1","version":"2026-07-18T19:15:00.000Z"},{"date_added":"2026-07-18T19:15:00.000Z","id":"indicator--54c6117b-c0a0-5a42-9efe-77f37d53d654","media_type":"application/stix+json;version=2.1","version":"2026-07-18T19:15:00.000Z"},{"date_added":"2026-07-18T19:15:00.000Z","id":"indicator--56f27bda-e299-53d1-8e84-cf0d52c5d479","media_type":"application/stix+json;version=2.1","version":"2026-07-18T19:15:00.000Z"},{"date_added":"2026-07-18T19:15:00.000Z","id":"indicator--78cd80ab-9888-5e4b-9e12-4344e5b29887","media_type":"application/stix+json;version=2.1","version":"2026-07-18T19:15:00.000Z"},{"date_added":"2026-07-18T19:15:00.000Z","id":"indicator--7d32b3ee-cb00-5241-98e7-f037db8ae82e","media_type":"application/stix+json;version=2.1","version":"2026-07-18T19:15:00.000Z"},{"date_added":"2026-07-18T19:15:00.000Z","id":"indicator--925d381c-b432-5892-98e0-7c9b76ef8a5f","media_type":"application/stix+json;version=2.1","version":"2026-07-18T19:15:00.000Z"},{"date_added":"2026-07-18T19:15:00.000Z","id":"indicator--93969723-e53a-5ed9-8528-69c84d5e73ee","media_type":"application/stix+json;version=2.1","version":"2026-07-18T19:15:00.000Z"},{"date_added":"2026-07-18T19:15:00.000Z","id":"indicator--9f94ec05-ad91-5561-8f2a-ed02f7f63f06","media_type":"application/stix+json;version=2.1","version":"2026-07-18T19:15:00.000Z"},{"date_added":"2026-07-18T19:15:00.000Z","id":"indicator--a7c4fb66-caad-50cd-bfd0-7b90bbb249b0","media_type":"application/stix+json;version=2.1","version":"2026-07-18T19:15:00.000Z"},{"date_added":"2026-07-18T19:15:00.000Z","id":"indicator--adee38c0-4bdf-52cb-90c8-209d92ddcd60","media_type":"application/stix+json;version=2.1","version":"2026-07-18T19:15:00.000Z"},{"date_added":"2026-07-18T19:15:00.000Z","id":"indicator--ba105e54-a950-57ab-8f47-ce8edd990e1e","media_type":"application/stix+json;version=2.1","version":"2026-07-18T19:15:00.000Z"},{"date_added":"2026-07-18T19:15:00.000Z","id":"indicator--c4271928-73d3-5594-8309-c88128f0b406","media_type":"application/stix+json;version=2.1","version":"2026-07-18T19:15:00.000Z"},{"date_added":"2026-07-18T19:15:00.000Z","id":"indicator--c984b34d-806e-56d5-8e8d-eab9a0901948","media_type":"application/stix+json;version=2.1","version":"2026-07-18T19:15:00.000Z"},{"date_added":"2026-07-18T19:15:00.000Z","id":"indicator--d817f9f3-be09-527b-ae7e-dbc3c0c47c90","media_type":"application/stix+json;version=2.1","version":"2026-07-18T19:15:00.000Z"},{"date_added":"2026-07-18T19:15:00.000Z","id":"indicator--d88e82e0-b29a-50d5-b6ab-1472224ea35c","media_type":"application/stix+json;version=2.1","version":"2026-07-18T19:15:00.000Z"},{"date_added":"2026-07-18T19:15:00.000Z","id":"indicator--dc8148ca-b797-5ff9-9b10-524028874caa","media_type":"application/stix+json;version=2.1","version":"2026-07-18T19:15:00.000Z"},{"date_added":"2026-07-18T19:15:00.000Z","id":"indicator--eb118e69-740a-5906-b07a-6fc6190e7f4c","media_type":"application/stix+json;version=2.1","version":"2026-07-18T19:15:00.000Z"},{"date_added":"2026-07-18T19:15:00.000Z","id":"indicator--f4a12c65-86f1-54f1-be1e-e84b788d8cbf","media_type":"application/stix+json;version=2.1","version":"2026-07-18T19:15:00.000Z"},{"date_added":"2026-07-18T21:17:00.000Z","id":"indicator--03664e3c-9c86-5cf3-9433-3d85d7f42709","media_type":"application/stix+json;version=2.1","version":"2026-07-18T21:17:00.000Z"},{"date_added":"2026-07-18T21:17:00.000Z","id":"indicator--0368460a-a68f-5ecf-ad93-1d4f92f162ec","media_type":"application/stix+json;version=2.1","version":"2026-07-18T21:17:00.000Z"},{"date_added":"2026-07-18T21:17:00.000Z","id":"indicator--3d080674-15bc-596d-81c0-6246fe4e1555","media_type":"application/stix+json;version=2.1","version":"2026-07-18T21:17:00.000Z"},{"date_added":"2026-07-18T21:17:00.000Z","id":"indicator--65b4b654-6113-57bd-a58b-3fb7c4cba17d","media_type":"application/stix+json;version=2.1","version":"2026-07-18T21:17:00.000Z"},{"date_added":"2026-07-18T21:17:00.000Z","id":"indicator--7ba52626-3b6e-5fd1-a817-4bb4e3652f06","media_type":"application/stix+json;version=2.1","version":"2026-07-18T21:17:00.000Z"},{"date_added":"2026-07-18T21:17:00.000Z","id":"indicator--8d21b73f-5d9e-511f-88cb-8e50aa149893","media_type":"application/stix+json;version=2.1","version":"2026-07-18T21:17:00.000Z"},{"date_added":"2026-07-18T21:17:00.000Z","id":"indicator--9b80d566-e345-5b4a-81f2-76c9923f088e","media_type":"application/stix+json;version=2.1","version":"2026-07-18T21:17:00.000Z"},{"date_added":"2026-07-18T21:17:00.000Z","id":"indicator--9ddf8b53-b609-5d82-b3ce-eca732569dd6","media_type":"application/stix+json;version=2.1","version":"2026-07-18T21:17:00.000Z"},{"date_added":"2026-07-18T21:17:00.000Z","id":"indicator--cfff6cd6-eae0-5ba9-9e86-c23900f4d227","media_type":"application/stix+json;version=2.1","version":"2026-07-18T21:17:00.000Z"}]